viewscad/__init__.py
viewscad/renderer-Copy1.py
viewscad/renderer.py
viewscad-0.2.0.dist-info/LICENSE
viewscad-0.2.0.dist-info/METADATA
viewscad-0.2.0.dist-info/WHEEL
viewscad-0.2.0.dist-info/top_level.txt
viewscad-0.2.0.dist-info/RECORD
